__init__.py
decorules/decorators.py
decorules/has_rules_actions.py
decorules/predicates.py
decorules/utils.py
example/client_class.py
example/library_class.py
decorules-0.0.9.dist-info/LICENSE
decorules-0.0.9.dist-info/METADATA
decorules-0.0.9.dist-info/WHEEL
decorules-0.0.9.dist-info/top_level.txt
decorules-0.0.9.dist-info/RECORD
