Metadata-Version: 2.1
Name: decorules
Version: 0.0.9
Summary: decorules is a tiny library that seeks to enforce class structure and instance behaviour on classes and their derived classes through decorators at class declaration time
Author-email: hraoyama <hraoyama@gmail.com>
Project-URL: Homepage, https://github.com/hraoyama/decorules
Project-URL: Issues, https://github.com/hraoyama/decorules/issues
Classifier: Programming Language :: Python :: 3
Classifier: License :: OSI Approved :: MIT License
Classifier: Operating System :: OS Independent
Requires-Python: >=3.10
License-File: LICENSE
